generate-ssm-parameters/__init__.py
generate-ssm-parameters/generate_ssm_parameters.py
generate-ssm-parameters/main.py
generate_ssm_parameters/__init__.py
generate_ssm_parameters/gen_ssm_params.py
generate_ssm_parameters-0.1.17.dist-info/LICENSE
generate_ssm_parameters-0.1.17.dist-info/METADATA
generate_ssm_parameters-0.1.17.dist-info/WHEEL
generate_ssm_parameters-0.1.17.dist-info/entry_points.txt
generate_ssm_parameters-0.1.17.dist-info/top_level.txt
generate_ssm_parameters-0.1.17.dist-info/RECORD
