Metadata-Version: 2.1
Name: generate-ssm-parameters
Version: 0.1.17
Summary: A script for creating AWS SSM Parameters in bulk from a CSV file.
Home-page: https://github.com/travers-co/generate-ssm-parameters
Author: Travers Annan
Author-email: travers@curiousorbit.com
License: MIT
Classifier: Programming Language :: Python :: 3
Classifier: Programming Language :: Python :: 3.7
Classifier: Programming Language :: Python :: 3.8
Classifier: Programming Language :: Python :: 3.9
Requires-Python: >=3.7
License-File: LICENSE
Requires-Dist: boto3 (>1.24.0)
Requires-Dist: botocore (>1.12.0)
Requires-Dist: click (>7.0.0)
Requires-Dist: pandas (>1.1.5)
Requires-Dist: tqdm (>4.0.0)
